metrohash.cpython-37m-x86_64-linux-gnu.so
metrohash_python-1.1.3.3.dist-info/LICENSE
metrohash_python-1.1.3.3.dist-info/METADATA
metrohash_python-1.1.3.3.dist-info/top_level.txt
metrohash_python-1.1.3.3.dist-info/RECORD
metrohash_python-1.1.3.3.dist-info/WHEEL
